livekit/plugins/soniox/__init__.py
livekit/plugins/soniox/log.py
livekit/plugins/soniox/py.typed
livekit/plugins/soniox/stt.py
livekit/plugins/soniox/version.py
livekit_plugins_soniox-1.3.11.dist-info/METADATA
livekit_plugins_soniox-1.3.11.dist-info/WHEEL
livekit_plugins_soniox-1.3.11.dist-info/RECORD
